volkanoban/__init__.py
volkanoban/classifier.py
volkanoban-0.1.23.dist-info/LICENCE.txt
volkanoban-0.1.23.dist-info/METADATA
volkanoban-0.1.23.dist-info/WHEEL
volkanoban-0.1.23.dist-info/top_level.txt
volkanoban-0.1.23.dist-info/RECORD
