Metadata-Version: 2.1
Name: volkanoban
Version: 0.1.23
Summary: A powerful stacking classifier framework that integrates advanced machine learning techniques, overfitting prevention, and explainability features such as LIME, SHAP, and model interpretation dashboards.
Author: Dr. Volkan OBAN
Author-email: volkanobn@gmail.com
Classifier: Programming Language :: Python :: 3
Classifier: Operating System :: OS Independent
Classifier: Development Status :: 4 - Beta
Classifier: Intended Audience :: Developers
Classifier: Intended Audience :: Science/Research
Classifier: Topic :: Scientific/Engineering :: Artificial Intelligence
Requires-Python: >=3.8
License-File: LICENCE.txt
Requires-Dist: numpy
Requires-Dist: pandas
Requires-Dist: scikit-learn
Requires-Dist: xgboost
Requires-Dist: lightgbm
Requires-Dist: catboost
Requires-Dist: lime
Requires-Dist: shap
Requires-Dist: explainerdashboard
Requires-Dist: plotly
Requires-Dist: tabulate
